spry/__init__.py
spry/__main__.py
spry/spry.py
spry/modules/__init__.py
spry/modules/core.py
spry/modules/pdf_maker.py
spry/modules/spinner.py
spry/modules/stuff.py
spry/modules/useragents.py
spry-0.5.7.dist-info/licenses/LICENSE
spry-0.5.7.dist-info/METADATA
spry-0.5.7.dist-info/WHEEL
spry-0.5.7.dist-info/entry_points.txt
spry-0.5.7.dist-info/top_level.txt
spry-0.5.7.dist-info/RECORD
