Metadata-Version: 2.4
Name: spry
Version: 0.5.7
Summary: social media scanner
Home-page: https://github.com/jamesacampbell/spry
Download-URL: https://github.com/jamesacampbell/spry/tarball/0.5.7
Author: James A. Campbell
Author-email: "James A. Campbell" <james@jamescampbell.us>
License-Expression: GPL-3.0
Project-URL: Homepage, https://github.com/jamesacampbell/spry
Project-URL: Repository, https://github.com/jamesacampbell/spry
Project-URL: Documentation, http://spry.rtfd.io
Keywords: social,collector,scraper
Classifier: Development Status :: 4 - Beta
Classifier: Environment :: Console
Classifier: Programming Language :: Python
Classifier: Operating System :: OS Independent
Classifier: Programming Language :: Python :: 3
Classifier: Programming Language :: Python :: 3.12
Classifier: Programming Language :: Python :: 3.13
Classifier: Programming Language :: Python :: 3.14
Requires-Python: >=3.12
License-File: LICENSE
Requires-Dist: requests
Requires-Dist: clint
Requires-Dist: fpdf
Requires-Dist: beautifulsoup4
Requires-Dist: termcolor
Requires-Dist: pysocks
Requires-Dist: weasyprint
Dynamic: author
Dynamic: download-url
Dynamic: home-page
Dynamic: license-file
Dynamic: requires-python
